targe/__init__.py
targe/__version__.py
targe/actor.py
targe/audit.py
targe/auth.py
targe/errors.py
targe/policy.py
targe/py.typed
targe/role.py
targe/utils.py
targe-0.4.0.dist-info/LICENSE
targe-0.4.0.dist-info/WHEEL
targe-0.4.0.dist-info/METADATA
targe-0.4.0.dist-info/RECORD
