Metadata-Version: 2.1
Name: targe
Version: 0.4.0
Summary: Powerful and flexible policy based authorization library.
Home-page: https://github.com/kodemore/targe
License: MIT
Keywords: authorization,acl,rbac,policy,auth,role,permissions
Author: Dawid Kraczkowski
Author-email: dawid.kraczkowski@gmail.com
Requires-Python: >=3.8,<4.0
Classifier: Development Status :: 5 - Production/Stable
Classifier: Intended Audience :: Developers
Classifier: License :: OSI Approved :: MIT License
Classifier: Natural Language :: English
Classifier: Programming Language :: Python
Classifier: Programming Language :: Python :: 3
Classifier: Programming Language :: Python :: 3.8
Classifier: Programming Language :: Python :: 3.9
Classifier: Programming Language :: Python :: 3.10
Classifier: Programming Language :: Python :: 3.11
Classifier: Programming Language :: Python :: 3.8
Classifier: Programming Language :: Python :: 3.9
Classifier: Topic :: Software Development :: Libraries
Classifier: Topic :: Software Development :: Libraries :: Python Modules
Classifier: Topic :: Utilities
Requires-Dist: gaffe (>=0.2.0,<0.3.0)
Requires-Dist: gid (>=1.0.1,<2.0.0)
Project-URL: Documentation, https://github.com/kodemore/targe
Project-URL: Repository, https://github.com/kodemore/targe
